gpt_engineer/__init__.py
gpt_engineer/applications/__init__.py
gpt_engineer/applications/cli/__init__.py
gpt_engineer/applications/cli/cli_agent.py
gpt_engineer/applications/cli/collect.py
gpt_engineer/applications/cli/file_selector.py
gpt_engineer/applications/cli/gpt_engineer_client.py
gpt_engineer/applications/cli/learning.py
gpt_engineer/applications/cli/main.py
gpt_engineer/benchmark/__init__.py
gpt_engineer/benchmark/__main__.py
gpt_engineer/benchmark/bench_config.py
gpt_engineer/benchmark/benchmarks/apps/load.py
gpt_engineer/benchmark/benchmarks/apps/problem.py
gpt_engineer/benchmark/benchmarks/apps/problems.py
gpt_engineer/benchmark/benchmarks/gptme/load.py
gpt_engineer/benchmark/benchmarks/load.py
gpt_engineer/benchmark/benchmarks/mbpp/load.py
gpt_engineer/benchmark/benchmarks/mbpp/problem.py
gpt_engineer/benchmark/benchmarks/mbpp/problems.py
gpt_engineer/benchmark/default_bench_config.toml
gpt_engineer/benchmark/run.py
gpt_engineer/benchmark/types.py
gpt_engineer/core/__init__.py
gpt_engineer/core/ai.py
gpt_engineer/core/base_agent.py
gpt_engineer/core/base_execution_env.py
gpt_engineer/core/base_memory.py
gpt_engineer/core/chat_to_files.py
gpt_engineer/core/default/__init__.py
gpt_engineer/core/default/constants.py
gpt_engineer/core/default/disk_execution_env.py
gpt_engineer/core/default/disk_memory.py
gpt_engineer/core/default/file_store.py
gpt_engineer/core/default/paths.py
gpt_engineer/core/default/simple_agent.py
gpt_engineer/core/default/steps.py
gpt_engineer/core/diff.py
gpt_engineer/core/files_dict.py
gpt_engineer/core/git.py
gpt_engineer/core/linting.py
gpt_engineer/core/preprompts_holder.py
gpt_engineer/core/project_config.py
gpt_engineer/core/prompt.py
gpt_engineer/core/token_usage.py
gpt_engineer/core/version_manager.py
gpt_engineer/preprompts/clarify
gpt_engineer/preprompts/entrypoint
gpt_engineer/preprompts/file_format
gpt_engineer/preprompts/file_format_diff
gpt_engineer/preprompts/file_format_fix
gpt_engineer/preprompts/generate
bella_engineer-0.3.1.dist-info/LICENSE
bella_engineer-0.3.1.dist-info/METADATA
bella_engineer-0.3.1.dist-info/WHEEL
bella_engineer-0.3.1.dist-info/entry_points.txt
bella_engineer-0.3.1.dist-info/RECORD
