Metadata-Version: 2.1
Name: bella-engineer
Version: 0.3.1
Summary: Specify what you want it to build, the AI asks for clarification, and then builds it.
Home-page: https://github.com/gpt-engineer-org/gpt-engineer
License: MIT
Author: Stan Sai
Author-email: saizhuolin@gmail.com
Requires-Python: >=3.10,<3.13
Classifier: Development Status :: 4 - Beta
Classifier: License :: OSI Approved :: MIT License
Classifier: Programming Language :: Python :: 3
Classifier: Programming Language :: Python :: 3.10
Classifier: Programming Language :: Python :: 3.11
Classifier: Topic :: Scientific/Engineering :: Artificial Intelligence
Provides-Extra: doc
Provides-Extra: test
Requires-Dist: black (==23.3.0)
Requires-Dist: dataclasses-json (==0.5.7)
Requires-Dist: datasets (>=2.17.1,<3.0.0)
Requires-Dist: javalang (>=0.13.0)
Requires-Dist: jsbeautifier (>=1.14.0)
Requires-Dist: langchain (>=0.1.2)
Requires-Dist: langchain-anthropic (>=0.1.1,<0.2.0)
Requires-Dist: langchain-community (>=0.2.0,<0.3.0)
Requires-Dist: langchain_openai
Requires-Dist: openai (>=1.0,<2.0)
Requires-Dist: pillow (>=10.2.0,<11.0.0)
Requires-Dist: pydantic (==1.10.8)
Requires-Dist: pyperclip (>=1.8.2,<2.0.0)
Requires-Dist: python-dotenv (>=0.21.0)
Requires-Dist: regex (>=2023.12.25,<2024.0.0)
Requires-Dist: rudder-sdk-python (>=2.0.2)
Requires-Dist: tabulate (==0.9.0)
Requires-Dist: termcolor (==2.3.0)
Requires-Dist: tiktoken (>=0.0.4)
Requires-Dist: toml (>=0.10.2)
Requires-Dist: tomlkit (>=0.12.4,<0.13.0)
Requires-Dist: typer (>=0.3.2)
Project-URL: Documentation, https://gpt-engineer.readthedocs.io/en/latest/
Project-URL: Repository, https://github.com/gpt-engineer-org/gpt-engineer
